plain/staff/README.md
plain/staff/__init__.py
plain/staff/config.py
plain/staff/dates.py
plain/staff/default_settings.py
plain/staff/middleware.py
plain/staff/templates.py
plain/staff/toolbar.py
plain/staff/urls.py
plain/staff/assets/staff/chart.js
plain/staff/assets/staff/jquery-3.6.1.slim.min.js
plain/staff/assets/staff/list.js
plain/staff/assets/staff/popper.min.js
plain/staff/assets/staff/staff.css
plain/staff/assets/staff/staff.js
plain/staff/assets/staff/tippy-bundle.umd.min.js
plain/staff/assets/toolbar/toolbar.js
plain/staff/cards/__init__.py
plain/staff/cards/base.py
plain/staff/cards/charts.py
plain/staff/cards/tables.py
plain/staff/impersonate/README.md
plain/staff/impersonate/__init__.py
plain/staff/impersonate/middleware.py
plain/staff/impersonate/models.py
plain/staff/impersonate/permissions.py
plain/staff/impersonate/settings.py
plain/staff/impersonate/urls.py
plain/staff/impersonate/views.py
plain/staff/querystats/README.md
plain/staff/querystats/__init__.py
plain/staff/querystats/core.py
plain/staff/querystats/middleware.py
plain/staff/querystats/urls.py
plain/staff/querystats/views.py
plain/staff/templates/elements/staff/Checkbox.html
plain/staff/templates/elements/staff/CheckboxField.html
plain/staff/templates/elements/staff/FieldErrors.html
plain/staff/templates/elements/staff/Input.html
plain/staff/templates/elements/staff/InputField.html
plain/staff/templates/elements/staff/Label.html
plain/staff/templates/elements/staff/Select.html
plain/staff/templates/elements/staff/SelectField.html
plain/staff/templates/elements/staff/Submit.html
plain/staff/templates/querystats/querystats.html
plain/staff/templates/querystats/toolbar.html
plain/staff/templates/staff/base.html
plain/staff/templates/staff/delete.html
plain/staff/templates/staff/detail.html
plain/staff/templates/staff/form.html
plain/staff/templates/staff/index.html
plain/staff/templates/staff/list.html
plain/staff/templates/staff/page.html
plain/staff/templates/staff/search.html
plain_staff-0.13.2.dist-info/METADATA
plain_staff-0.13.2.dist-info/WHEEL
plain_staff-0.13.2.dist-info/licenses/LICENSE
plain_staff-0.13.2.dist-info/RECORD
