Metadata-Version: 2.4
Name: plain.staff
Version: 0.13.2
Summary: Staff dashboard and tools for Plain.
Author-email: Dave Gaeddert <dave.gaeddert@dropseed.dev>
License-Expression: BSD-3-Clause
License-File: LICENSE
Requires-Python: >=3.11
Requires-Dist: plain-auth<1.0.0
Requires-Dist: plain-htmx<1.0.0
Requires-Dist: plain-tailwind<1.0.0
Requires-Dist: plain<1.0.0
Requires-Dist: sqlparse>=0.2.2
